{
    "config": {
        "siteTitle": "UnderCMS",
        "logoName": "UnderCMS",
        "logoImage": "logo.png",
        "faviconImage": "favicon.png",
        "defaultPage": "index.html",
        "defaultMenu": "home",
        "style": "style.css",                      
        "activeAdminLogin": true,  
        "activeUserLogin": true,       
        "pageHeader": {
            "content": "UnderCMS is a simple, fast, and modern CMS.",
            "backgroundColor": "#cca463",
            "backgroundImage": ""
        },       
        "pageFooter": { 
            "content": "2023 Created by Devrazec.",
            "backgroundColor": "#cca463",
            "backgroundImage": ""
        }
    },   
    
    "menu": {
        "0": {
            "sort": "1",
            "name": "Home",
            "slug": "home",
            "page": "#section1",
            "externalLink": false,
            "active": true
        },
        "1": {
            "sort": "2",
            "name": "Services",
            "slug": "services",
            "page": "#section2",
            "externalLink": false,
            "active": true
        },
        "2": {
            "sort": "3",
            "name": "Portfolio",
            "slug": "portfolio",
            "page": "#section2",
            "externalLink": false,
            "active": true
        },
        "3": {
            "sort": "4",
            "name": "Resume",
            "slug": "resume",
            "page": "https://www.devrazec.com/assets/resume.pdf",
            "externalLink": true,
            "active": true
        },
        "4": {
            "sort": "5",
            "name": "Price",
            "slug": "price",
            "page": "price.html",
            "externalLink": false,
            "active": true
        },
        "5": {
            "sort": "6",
            "name": "Contact",
            "slug": "contact",
            "page": "https://www.linkedin.com/in/maxchip/",
            "externalLink": true,
            "active": true
        },
        "6": {
            "sort": "7",
            "name": "Users",
            "slug": "users",
            "page": "users.html",
            "externalLink": false,
            "active": false
        }
    },        
        
    "page": {        
        "0": {
            "sort": "1",
            "title": "Home",
            "menuSlug": "home",
            "keywords": "",
            "description": "",
            "content": "Welcome to your Home.",
            "image": "",
            "active": false 
        },
        "1": {
            "sort": "4",
            "title": "Services",
            "menuSlug": "services",
            "keywords": "",
            "description": "",
            "content": "Welcome to your Services.",
            "image": "",
            "active": true 
        },
        "2": {
            "sort": "2",
            "title": "Portfolio",
            "menuSlug": "portfolio",
            "keywords": "",
            "description": "",
            "content": "Welcome to your Portfolio.",
            "image": "",
            "active": true 
        },
        "3": {
            "sort": "3",
            "title": "Price",
            "menuSlug": "Price",
            "keywords": "",
            "description": "",           
            "content": "Welcome to your Price.",
            "image": "",
            "active": true 
        },
        "4": {
            "sort": "6",
            "title": "404",
            "menuSlug": "",
            "keywords": "404",
            "description": "404",            
            "content": "404 - Page not found",
            "image": "",
            "active": true            
        }          
    },    
    
    "post": {        
        "0": {
            "sort": "1",
            "title": "Post 1",            
            "date": "10 Sep 2023",
            "user": "Admin1",
            "keywords": "",
            "description": "",
            "content": "Post 1",
            "image": "",
            "active": false 
        },
        "1": {
            "sort": "4",
            "title": "Post 2",
            "date": "10 Sep 2023",
            "user": "Admin1",
            "keywords": "",
            "description": "",
            "content": "Post 2",
            "image": "",
            "active": true 
        },
        "2": {
            "sort": "2",
            "title": "Post 3",
            "date": "10 Sep 2023",
            "user": "Admin1",
            "keywords": "",
            "description": "",
            "content": "Post 3",
            "image": "",
            "active": true 
        },
        "3": {
            "sort": "3",
            "title": "Post 4",
            "date": "10 Sep 2023",
            "user": "Admin1",
            "keywords": "",
            "description": "",           
            "content": "Post 4",
            "image": "",
            "active": false 
        },
        "4": {
            "sort": "6",
            "title": "Post 5",
            "date": "10 Sep 2023",
            "user": "Admin1",
            "keywords": "",
            "description": "",            
            "content": "Post 5",
            "image": "",
            "active": true            
        }          
    } 
}